rustpython_ast_pyo3_wrapper-0.0.1.dist-info/METADATA
rustpython_ast_pyo3_wrapper-0.0.1.dist-info/WHEEL
rustpython_ast_pyo3_wrapper-0.0.1.dist-info/license_files/LICENSE
rustpython_ast_pyo3_wrapper/__init__.py
rustpython_ast_pyo3_wrapper/rustpython_ast_pyo3_wrapper.pypy310-pp73-x86_64-linux-gnu.so
rustpython_ast_pyo3_wrapper-0.0.1.dist-info/RECORD
