Metadata-Version: 2.1
Name: rustpython_ast_pyo3_wrapper
Version: 0.0.1
Classifier: Programming Language :: Rust
Classifier: Programming Language :: Python :: Implementation :: CPython
License-File: LICENSE
Summary: rustpython-ast PyO3 bindings using wrapper feature
Author: Jeong, Yunwon
License: MIT
Requires-Python: >=3.7
Project-URL: Homepage, https://github.com/hhclaw/
Project-URL: Repository, https://github.com/hhclaw/rustpython-ast-pyo3
Project-URL: Issues, https://github.com/hhclaw/rustpython-ast-pyo3/issues
